peacock_trame/__init__.py
peacock_trame/app/__init__.py
peacock_trame/app/__main__.py
peacock_trame/app/executor.py
peacock_trame/app/exodusViewer.py
peacock_trame/app/fileEditor.py
peacock_trame/app/jupyter.py
peacock_trame/app/main.py
peacock_trame/app/core/__init__.py
peacock_trame/app/core/common/ExeLauncher.py
peacock_trame/app/core/common/PeacockException.py
peacock_trame/app/core/common/__init__.py
peacock_trame/app/core/common/utils.py
peacock_trame/app/core/exodusViewer/__init__.py
peacock_trame/app/core/exodusViewer/time_step.py
peacock_trame/app/core/input/BlockInfo.py
peacock_trame/app/core/input/ExecutableInfo.py
peacock_trame/app/core/input/InputFile.py
peacock_trame/app/core/input/InputTree.py
peacock_trame/app/core/input/InputTreeWriter.py
peacock_trame/app/core/input/JsonData.py
peacock_trame/app/core/input/LanguageServer.py
peacock_trame/app/core/input/ParameterInfo.py
peacock_trame/app/core/input/__init__.py
peacock_trame/app/logos/peacock_logo.ico
peacock_trame/module/__init__.py
peacock_trame/module/serve/demo.html
peacock_trame/module/serve/editor.worker.js
peacock_trame/module/serve/editor.worker.js.map
peacock_trame/module/serve/onig.wasm
peacock_trame/module/serve/vue-peacock_trame.common.js
peacock_trame/module/serve/vue-peacock_trame.common.js.map
peacock_trame/module/serve/vue-peacock_trame.css
peacock_trame/module/serve/vue-peacock_trame.umd.js
peacock_trame/module/serve/vue-peacock_trame.umd.js.map
peacock_trame/module/serve/vue-peacock_trame.umd.min.js
peacock_trame/module/serve/vue-peacock_trame.umd.min.js.map
peacock_trame/module/serve/fonts/codicon.205bdf70.ttf
peacock_trame/widgets/__init__.py
peacock_trame/widgets/peacock.py
peacock_trame-0.1.2.dist-info/LICENSE
peacock_trame-0.1.2.dist-info/METADATA
peacock_trame-0.1.2.dist-info/WHEEL
peacock_trame-0.1.2.dist-info/entry_points.txt
peacock_trame-0.1.2.dist-info/top_level.txt
peacock_trame-0.1.2.dist-info/RECORD
