Metadata-Version: 2.1
Name: peacock-trame
Version: 0.1.2
Summary: MOOSE GUI developed using Trame from Kitware Inc.
Author: Elim Schenck
License: Apache Software License
Keywords: Python,Interactive,Web,Application,Framework
Classifier: Development Status :: 4 - Beta
Classifier: Environment :: Web Environment
Classifier: License :: OSI Approved :: Apache Software License
Classifier: Natural Language :: English
Classifier: Operating System :: OS Independent
Classifier: Programming Language :: Python :: 3 :: Only
Classifier: Programming Language :: JavaScript
Classifier: Topic :: Software Development :: Libraries :: Application Frameworks
Classifier: Topic :: Software Development :: Libraries :: Python Modules
License-File: LICENSE
Requires-Dist: trame
Requires-Dist: trame-vuetify
Requires-Dist: trame-vtk
Requires-Dist: trame-xterm
Requires-Dist: trame-simput
Requires-Dist: pyaml
Requires-Dist: numpy
